ppci/__init__.py
ppci/__main__.py
ppci/api.py
ppci/cil.py
ppci/common.py
ppci/instrument.py
ppci/ir.py
ppci/ir_link.py
ppci/irutils.py
ppci/runtime.py
ppci/arch/__init__.py
ppci/arch/arch.py
ppci/arch/arch_info.py
ppci/arch/asm_printer.py
ppci/arch/cc.py
ppci/arch/data_instructions.py
ppci/arch/effects.py
ppci/arch/encoding.py
ppci/arch/example.py
ppci/arch/generic_instructions.py
ppci/arch/isa.py
ppci/arch/registers.py
ppci/arch/runtime.py
ppci/arch/stack.py
ppci/arch/target_list.py
ppci/arch/token.py
ppci/arch/arm/__init__.py
ppci/arch/arm/arch.py
ppci/arch/arm/arm_instructions.py
ppci/arch/arm/arm_relocations.py
ppci/arch/arm/isa.py
ppci/arch/arm/neon.py
ppci/arch/arm/registers.py
ppci/arch/arm/thumb_instructions.py
ppci/arch/arm/thumb_relocations.py
ppci/arch/arm/vfp.py
ppci/arch/avr/__init__.py
ppci/arch/avr/arch.py
ppci/arch/avr/instructions.py
ppci/arch/avr/registers.py
ppci/arch/jvm/__init__.py
ppci/arch/jvm/__main__.py
ppci/arch/jvm/class2ir.py
ppci/arch/jvm/class_loader.py
ppci/arch/jvm/dynload.py
ppci/arch/jvm/enums.py
ppci/arch/jvm/io.py
ppci/arch/jvm/jarfile.py
ppci/arch/jvm/nodes.py
ppci/arch/jvm/opcodes.py
ppci/arch/jvm/printer.py
ppci/arch/m68k/__init__.py
ppci/arch/m68k/arch.py
ppci/arch/m68k/instructions.py
ppci/arch/m68k/registers.py
ppci/arch/mcs6500/__init__.py
ppci/arch/mcs6500/arch.py
ppci/arch/mcs6500/instructions.py
ppci/arch/mcs6500/registers.py
ppci/arch/microblaze/__init__.py
ppci/arch/microblaze/arch.py
ppci/arch/microblaze/instructions.py
ppci/arch/microblaze/registers.py
ppci/arch/mips/__init__.py
ppci/arch/mips/arch.py
ppci/arch/mips/instructions.py
ppci/arch/mips/registers.py
ppci/arch/msp430/__init__.py
ppci/arch/msp430/arch.py
ppci/arch/msp430/instructions.py
ppci/arch/msp430/registers.py
ppci/arch/or1k/__init__.py
ppci/arch/or1k/arch.py
ppci/arch/or1k/instructions.py
ppci/arch/or1k/isa.py
ppci/arch/or1k/orfpx32.py
ppci/arch/or1k/registers.py
ppci/arch/riscv/__init__.py
ppci/arch/riscv/arch.py
ppci/arch/riscv/asm_printer.py
ppci-0.5.8.dist-info/METADATA
ppci-0.5.8.dist-info/WHEEL
ppci-0.5.8.dist-info/entry_points.txt
ppci-0.5.8.dist-info/top_level.txt
ppci-0.5.8.dist-info/RECORD
