Metadata-Version: 2.1
Name: ppci
Version: 0.5.8
Summary: A compiler for ARM, X86, MSP430, xtensa and more implemented in pure Python
Home-page: https://ppci.readthedocs.io/
Author: Windel Bouwman
Author-email: UNKNOWN
License: BSD
Platform: UNKNOWN
Classifier: License :: OSI Approved :: BSD License
Classifier: Development Status :: 3 - Alpha
Classifier: Programming Language :: Assembly
Classifier: Programming Language :: C
Classifier: Programming Language :: Java
Classifier: Programming Language :: Python :: 3
Classifier: Programming Language :: Python :: 3.4
Classifier: Programming Language :: Python :: 3.5
Classifier: Programming Language :: Python :: 3.6
Classifier: Programming Language :: Python :: 3.7
Classifier: Programming Language :: Python :: Implementation :: CPython
Classifier: Programming Language :: Python :: Implementation :: PyPy
Classifier: Topic :: Software Development :: Compilers
Classifier: Topic :: Software Development :: Assemblers
Classifier: Topic :: Software Development :: Code Generators
Classifier: Topic :: Software Development :: Embedded Systems
Classifier: Topic :: Software Development :: Pre-processors
